flask_tweepy.py
setup.py
Flask_Tweepy.egg-info/PKG-INFO
Flask_Tweepy.egg-info/SOURCES.txt
Flask_Tweepy.egg-info/dependency_links.txt
Flask_Tweepy.egg-info/not-zip-safe
Flask_Tweepy.egg-info/requires.txt
Flask_Tweepy.egg-info/top_level.txt
test/test_config.py