Metadata-Version: 1.0
Name: Flask-Tweepy
Version: 0.1
Summary: Tweet easily from Flask applications
Home-page: http://flask-tweepy.readthedocs.org/
Author: Dan Crosta
Author-email: dcrosta@late.am
License: BSD
Platform: any
Classifier: Environment :: Web Environment
Classifier: Intended Audience :: Developers
Classifier: License :: OSI Approved :: BSD License
Classifier: Operating System :: OS Independent
Classifier: Programming Language :: Python
Classifier: Topic :: Internet :: WWW/HTTP :: Dynamic Content
Classifier: Topic :: Software Development :: Libraries :: Python Modules
